leap_sdk_pyo3-0.1.0.dist-info/METADATA
leap_sdk_pyo3-0.1.0.dist-info/WHEEL
leap_sdk_pyo3/__init__.py
leap_sdk_pyo3/leap_sdk_pyo3.cpython-310-darwin.so
leap_sdk_pyo3-0.1.0.dist-info/RECORD
